ur_gym/__init__.py
ur_gym/envs/__init__.py
ur_gym/envs/ur_env.py
IAS_ur5-0.0.1.dist-info/METADATA
IAS_ur5-0.0.1.dist-info/WHEEL
IAS_ur5-0.0.1.dist-info/top_level.txt
IAS_ur5-0.0.1.dist-info/RECORD
