Metadata-Version: 2.1
Name: IAS-ur5
Version: 0.0.1
Summary: IAS Lab ur5
Requires-Dist: gym
